[
  { "id":"ToLove-001",  "usertag":"",
    "img":"manga_slider/ToLove 001/1.webp",
    "html":"https://searis0002.github.io/searis-ToLove/manga_slider/ToLove%20001/index.html",
    "namer":"",
    "sitelink":"<a href=\"\">",
    "tag":"ToLoveる <br>かわいい"
  },
  { "id":"ToLove-002",  "usertag":"",
    "img":"manga_slider/ToLove 002/1.webp",
    "html":"https://searis0002.github.io/searis-ToLove/manga_slider/ToLove%20002/index.html",
    "namer":"",
    "sitelink":"<a href=\"\">",
    "tag":"ToLoveる <br>かわいい"
  },
  { "id":"ToLove-003",  "usertag":"",
    "img":"manga_slider/ToLove 003/1.webp",
    "html":"https://searis0002.github.io/searis-ToLove/manga_slider/ToLove%20003/index.html",
    "namer":"",
    "sitelink":"<a href=\"\">",
    "tag":"ToLoveる <br>かわいい"
  },
  { "id":"ToLove-004",  "usertag":"",
    "img":"manga_slider/ToLove 004/1.webp",
    "html":"https://searis0002.github.io/searis-ToLove/manga_slider/ToLove%20004/index.html",
    "namer":"",
    "sitelink":"<a href=\"\">",
    "tag":"ToLoveる <br>かわいい"
  }
]

